<?xml version="1.0" encoding="utf-8"?><?xml-stylesheet type="text/xsl" href="styletable.xsl"?><table xmlns:dt="urn:schemas-microsoft-com:datatypes"><records id="th1_64"><rec id="th1rec3969"><ext>3849.762,3927.985,3096.84,3232.713</ext><ts extId="0" /><c><f0>3969</f0><f1>Lumbini</f1><f2>Arghakhanchi</f2><f3>Maidan</f3><f4>50027</f4><f5>524 3 09 50 5 030</f5><f6 dt:dt="float" /><f7 dt:dt="float" /><f8 dt:dt="float" /><f9 dt:dt="float" /><f10 dt:dt="float" /><f11 dt:dt="float" /><f12 dt:dt="float" /><f13 dt:dt="float" /><f14 dt:dt="float" /><f15 dt:dt="float" /><f16 dt:dt="float" /><f17 dt:dt="float" /><f18 /><f19 /><f20 /><f21 /><f22 /><f23 /><f24 /><f25 /><f26 /><f27 /><f28 /><f29 /><f30>Arghakhanchi</f30></c></rec><rec id="th1rec3970"><ext>3801.879,3874.353,2896.035,2957.468</ext><ts extId="0" /><c><f0>3970</f0><f1>Lumbini</f1><f2>Arghakhanchi</f2><f3>Mareng</f3><f4>50028</f4><f5>524 3 09 50 5 018</f5><f6 dt:dt="float" /><f7 dt:dt="float" /><f8 dt:dt="float" /><f9 dt:dt="float" /><f10 dt:dt="float" /><f11 dt:dt="float" /><f12 dt:dt="float" /><f13 dt:dt="float" /><f14 dt:dt="float" /><f15 dt:dt="float" /><f16 dt:dt="float" /><f17 dt:dt="float" /><f18 /><f19 /><f20 /><f21 /><f22 /><f23 /><f24 /><f25 /><f26 /><f27 /><f28 /><f29 /><f30>Arghakhanchi</f30></c></rec><rec id="th1rec3971"><ext>3777.524,3840.869,3054.287,3138.395</ext><ts extId="0" /><c><f0>3971</f0><f1>Lumbini</f1><f2>Arghakhanchi</f2><f3>Narapani</f3><f4>50029</f4><f5>524 3 09 50 5 023</f5><f6 dt:dt="float" /><f7 dt:dt="float" /><f8 dt:dt="float" /><f9 dt:dt="float" /><f10 dt:dt="float" /><f11 dt:dt="float" /><f12 dt:dt="float" /><f13 dt:dt="float" /><f14 dt:dt="float" /><f15 dt:dt="float" /><f16 dt:dt="float" /><f17 dt:dt="float" /><f18 /><f19 /><f20 /><f21 /><f22 /><f23 /><f24 /><f25 /><f26 /><f27 /><f28 /><f29 /><f30>Arghakhanchi</f30></c></rec><rec id="th1rec3972"><ext>3625.223,3730.522,3007.919,3082.886</ext><ts extId="0" /><c><f0>3972</f0><f1>Lumbini</f1><f2>Arghakhanchi</f2><f3>Nuwakot</f3><f4>50030</f4><f5>524 3 09 50 5 041</f5><f6 dt:dt="float" /><f7 dt:dt="float" /><f8 dt:dt="float" /><f9 dt:dt="float" /><f10 dt:dt="float" /><f11 dt:dt="float" /><f12 dt:dt="float" /><f13 dt:dt="float" /><f14 dt:dt="float" /><f15 dt:dt="float" /><f16 dt:dt="float" /><f17 dt:dt="float" /><f18 /><f19 /><f20 /><f21 /><f22 /><f23 /><f24 /><f25 /><f26 /><f27 /><f28 /><f29 /><f30>Arghakhanchi</f30></c></rec><rec id="th1rec3973"><ext>3845.425,3946.408,3042.1,3104.149</ext><ts extId="0" /><c><f0>3973</f0><f1>Lumbini</f1><f2>Arghakhanchi</f2><f3>Pali</f3><f4>50031</f4><f5>524 3 09 50 5 024</f5><f6 dt:dt="float" /><f7 dt:dt="float" /><f8 dt:dt="float" /><f9 dt:dt="float" /><f10 dt:dt="float" /><f11 dt:dt="float" /><f12 dt:dt="float" /><f13 dt:dt="float" /><f14 dt:dt="float" /><f15 dt:dt="float" /><f16 dt:dt="float" /><f17 dt:dt="float" /><f18 /><f19 /><f20 /><f21 /><f22 /><f23 /><f24 /><f25 /><f26 /><f27 /><f28 /><f29 /><f30>Arghakhanchi</f30></c></rec><rec id="th1rec3974"><ext>3898.841,3951.89,3131.015,3216.577</ext><ts extId="0" /><c><f0>3974</f0><f1>Lumbini</f1><f2>Arghakhanchi</f2><f3>Patauti</f3><f4>50033</f4><f5>524 3 09 50 5 027</f5><f6 dt:dt="float" /><f7 dt:dt="float" /><f8 dt:dt="float" /><f9 dt:dt="float" /><f10 dt:dt="float" /><f11 dt:dt="float" /><f12 dt:dt="float" /><f13 dt:dt="float" /><f14 dt:dt="float" /><f15 dt:dt="float" /><f16 dt:dt="float" /><f17 dt:dt="float" /><f18 /><f19 /><f20 /><f21 /><f22 /><f23 /><f24 /><f25 /><f26 /><f27 /><f28 /><f29 /><f30>Arghakhanchi</f30></c></rec><rec id="th1rec3975"><ext>3955.389,4015.847,3136.198,3179.204</ext><ts extId="0" /><c><f0>3975</f0><f1>Lumbini</f1><f2>Arghakhanchi</f2><f3>Panena</f3><f4>50032</f4><f5>524 3 09 50 5 026</f5><f6 dt:dt="float" /><f7 dt:dt="float" /><f8 dt:dt="float" /><f9 dt:dt="float" /><f10 dt:dt="float" /><f11 dt:dt="float" /><f12 dt:dt="float" /><f13 dt:dt="float" /><f14 dt:dt="float" /><f15 dt:dt="float" /><f16 dt:dt="float" /><f17 dt:dt="float" /><f18 /><f19 /><f20 /><f21 /><f22 /><f23 /><f24 /><f25 /><f26 /><f27 /><f28 /><f29 /><f30>Arghakhanchi</f30></c></rec><rec id="th1rec3976"><ext>3914.786,3990.835,3130.546,3217.315</ext><ts extId="0" /><c><f0>3976</f0><f1>Lumbini</f1><f2>Arghakhanchi</f2><f3>Pokharathok</f3><f4>50034</f4><f5>524 3 09 50 5 028</f5><f6 dt:dt="float" /><f7 dt:dt="float" /><f8 dt:dt="float" /><f9 dt:dt="float" /><f10 dt:dt="float" /><f11 dt:dt="float" /><f12 dt:dt="float" /><f13 dt:dt="float" /><f14 dt:dt="float" /><f15 dt:dt="float" /><f16 dt:dt="float" /><f17 dt:dt="float" /><f18 /><f19 /><f20 /><f21 /><f22 /><f23 /><f24 /><f25 /><f26 /><f27 /><f28 /><f29 /><f30>Arghakhanchi</f30></c></rec><rec id="th1rec3977"><ext>3725.967,3809.532,3004.948,3061.528</ext><ts extId="0" /><c><f0>3977</f0><f1>Lumbini</f1><f2>Arghakhanchi</f2><f3>Sandhikharka</f3><f4>50035</f4><f5>524 3 09 50 5 042</f5><f6 dt:dt="float" /><f7 dt:dt="float" /><f8 dt:dt="float" /><f9 dt:dt="float" /><f10 dt:dt="float" /><f11 dt:dt="float" /><f12 dt:dt="float" /><f13 dt:dt="float" /><f14 dt:dt="float" /><f15 dt:dt="float" /><f16 dt:dt="float" /><f17 dt:dt="float" /><f18 /><f19 /><f20 /><f21 /><f22 /><f23 /><f24 /><f25 /><f26 /><f27 /><f28 /><f29 /><f30>Arghakhanchi</f30></c></rec><rec id="th1rec3978"><ext>3361.713,3642.809,3128.047,3268.342</ext><ts extId="0" /><c><f0>3978</f0><f1>Lumbini</f1><f2>Arghakhanchi</f2><f3>Siddhara</f3><f4>50036</f4><f5>524 3 09 50 5 037</f5><f6 dt:dt="float" /><f7 dt:dt="float" /><f8 dt:dt="float" /><f9 dt:dt="float" /><f10 dt:dt="float" /><f11 dt:dt="float" /><f12 dt:dt="float" /><f13 dt:dt="float" /><f14 dt:dt="float" /><f15 dt:dt="float" /><f16 dt:dt="float" /><f17 dt:dt="float" /><f18 /><f19 /><f20 /><f21 /><f22 /><f23 /><f24 /><f25 /><f26 /><f27 /><f28 /><f29 /><f30>Arghakhanchi</f30></c></rec><rec id="th1rec3979"><ext>3740.386,3927.584,3203.286,3310.027</ext><ts extId="0" /><c><f0>3979</f0><f1>Lumbini</f1><f2>Arghakhanchi</f2><f3>Simalpani</f3><f4>50037</f4><f5>524 3 09 50 5 032</f5><f6 dt:dt="float" /><f7 dt:dt="float" /><f8 dt:dt="float" /><f9 dt:dt="float" /><f10 dt:dt="float" /><f11 dt:dt="float" /><f12 dt:dt="float" /><f13 dt:dt="float" /><f14 dt:dt="float" /><f15 dt:dt="float" /><f16 dt:dt="float" /><f17 dt:dt="float" /><f18 /><f19 /><f20 /><f21 /><f22 /><f23 /><f24 /><f25 /><f26 /><f27 /><f28 /><f29 /><f30>Arghakhanchi</f30></c></rec><rec id="th1rec3980"><ext>3739.022,3811.245,3110.405,3207.986</ext><ts extId="0" /><c><f0>3980</f0><f1>Lumbini</f1><f2>Arghakhanchi</f2><f3>Sitapur</f3><f4>50038</f4><f5>524 3 09 50 5 031</f5><f6 dt:dt="float" /><f7 dt:dt="float" /><f8 dt:dt="float" /><f9 dt:dt="float" /><f10 dt:dt="float" /><f11 dt:dt="float" /><f12 dt:dt="float" /><f13 dt:dt="float" /><f14 dt:dt="float" /><f15 dt:dt="float" /><f16 dt:dt="float" /><f17 dt:dt="float" /><f18 /><f19 /><f20 /><f21 /><f22 /><f23 /><f24 /><f25 /><f26 /><f27 /><f28 /><f29 /><f30>Arghakhanchi</f30></c></rec><rec id="th1rec3981"><ext>3780.714,3867.662,3136.634,3212.216</ext><ts extId="0" /><c><f0>3981</f0><f1>Lumbini</f1><f2>Arghakhanchi</f2><f3>Suwarnakhal</f3><f4>50039</f4><f5>524 3 09 50 5 033</f5><f6 dt:dt="float" /><f7 dt:dt="float" /><f8 dt:dt="float" /><f9 dt:dt="float" /><f10 dt:dt="float" /><f11 dt:dt="float" /><f12 dt:dt="float" /><f13 dt:dt="float" /><f14 dt:dt="float" /><f15 dt:dt="float" /><f16 dt:dt="float" /><f17 dt:dt="float" /><f18 /><f19 /><f20 /><f21 /><f22 /><f23 /><f24 /><f25 /><f26 /><f27 /><f28 /><f29 /><f30>Arghakhanchi</f30></c></rec><rec id="th1rec3982"><ext>3629.898,3781.288,3108.221,3302.262</ext><ts extId="0" /><c><f0>3982</f0><f1>Lumbini</f1><f2>Arghakhanchi</f2><f3>Thada</f3><f4>50040</f4><f5>524 3 09 50 5 038</f5><f6 dt:dt="float" /><f7 dt:dt="float" /><f8 dt:dt="float" /><f9 dt:dt="float" /><f10 dt:dt="float" /><f11 dt:dt="float" /><f12 dt:dt="float" /><f13 dt:dt="float" /><f14 dt:dt="float" /><f15 dt:dt="float" /><f16 dt:dt="float" /><f17 dt:dt="float" /><f18 /><f19 /><f20 /><f21 /><f22 /><f23 /><f24 /><f25 /><f26 /><f27 /><f28 /><f29 /><f30>Arghakhanchi</f30></c></rec><rec id="th1rec3983"><ext>3830.249,3866.862,2967.421,3030.506</ext><ts extId="0" /><c><f0>3983</f0><f1>Lumbini</f1><f2>Arghakhanchi</f2><f3>Thulopokhari</f3><f4>50041</f4><f5>524 3 09 50 5 019</f5><f6 dt:dt="float" /><f7 dt:dt="float" /><f8 dt:dt="float" /><f9 dt:dt="float" /><f10 dt:dt="float" /><f11 dt:dt="float" /><f12 dt:dt="float" /><f13 dt:dt="float" /><f14 dt:dt="float" /><f15 dt:dt="float" /><f16 dt:dt="float" /><f17 dt:dt="float" /><f18 /><f19 /><f20 /><f21 /><f22 /><f23 /><f24 /><f25 /><f26 /><f27 /><f28 /><f29 /><f30>Arghakhanchi</f30></c></rec></records></table>